{
  "version": "6",
  "dialect": "sqlite",
  "id": "04a17a52-855e-4bb3-b3f9-fa7c57d51942",
  "prevId": "7cd5d462-9ac9-4a94-bf4b-2acf17640f5e",
  "tables": {
    "accounts": {
      "name": "accounts",
      "columns": {
        "id": {
          "name": "id",
          "type": "text",
          "primaryKey": true,
          "notNull": true,
          "autoincrement": false
        },
        "name": {
          "name": "name",
          "type": "text",
          "primaryKey": false,
          "notNull": true,
          "autoincrement": false
        },
        "type": {
          "name": "type",
          "type": "text",
          "primaryKey": false,
          "notNull": true,
          "autoincrement": false
        },
        "initial_balance_cents": {
          "name": "initial_balance_cents",
          "type": "integer",
          "primaryKey": false,
          "notNull": true,
          "autoincrement": false,
          "default": 0
        },
        "credit_closing_day": {
          "name": "credit_closing_day",
          "type": "integer",
          "primaryKey": false,
          "notNull": false,
          "autoincrement": false
        },
        "credit_due_day": {
          "name": "credit_due_day",
          "type": "integer",
          "primaryKey": false,
          "notNull": true,
          "autoincrement": false,
          "default": 10
        },
        "is_archived": {
          "name": "is_archived",
          "type": "integer",
          "primaryKey": false,
          "notNull": true,
          "autoincrement": false,
          "default": false
        },
        "created_at": {
          "name": "created_at",
          "type": "integer",
          "primaryKey": false,
          "notNull": true,
          "autoincrement": false,
          "default": "(unixepoch() * 1000)"
        },
        "updated_at": {
          "name": "updated_at",
          "type": "integer",
          "primaryKey": false,
          "notNull": true,
          "autoincrement": false,
          "default": "(unixepoch() * 1000)"
        }
      },
      "indexes": {
        "accounts_name_unique": {
          "name": "accounts_name_unique",
          "columns": [
            "name"
          ],
          "isUnique": true
        }
      },
      "foreignKeys": {},
      "compositePrimaryKeys": {},
      "uniqueConstraints": {},
      "checkConstraints": {}
    },
    "categories": {
      "name": "categories",
      "columns": {
        "id": {
          "name": "id",
          "type": "text",
          "primaryKey": true,
          "notNull": true,
          "autoincrement": false
        },
        "name": {
          "name": "name",
          "type": "text",
          "primaryKey": false,
          "notNull": true,
          "autoincrement": false
        },
        "group": {
          "name": "group",
          "type": "text",
          "primaryKey": false,
          "notNull": true,
          "autoincrement": false
        },
        "is_archived": {
          "name": "is_archived",
          "type": "integer",
          "primaryKey": false,
          "notNull": true,
          "autoincrement": false,
          "default": false
        },
        "created_at": {
          "name": "created_at",
          "type": "integer",
          "primaryKey": false,
          "notNull": true,
          "autoincrement": false,
          "default": "(unixepoch() * 1000)"
        },
        "updated_at": {
          "name": "updated_at",
          "type": "integer",
          "primaryKey": false,
          "notNull": true,
          "autoincrement": false,
          "default": "(unixepoch() * 1000)"
        }
      },
      "indexes": {
        "categories_name_unique": {
          "name": "categories_name_unique",
          "columns": [
            "name"
          ],
          "isUnique": true
        }
      },
      "foreignKeys": {},
      "compositePrimaryKeys": {},
      "uniqueConstraints": {},
      "checkConstraints": {}
    },
    "credit_card_charges": {
      "name": "credit_card_charges",
      "columns": {
        "id": {
          "name": "id",
          "type": "text",
          "primaryKey": true,
          "notNull": true,
          "autoincrement": false
        },
        "account_id": {
          "name": "account_id",
          "type": "text",
          "primaryKey": false,
          "notNull": true,
          "autoincrement": false
        },
        "category_id": {
          "name": "category_id",
          "type": "text",
          "primaryKey": false,
          "notNull": true,
          "autoincrement": false
        },
        "description": {
          "name": "description",
          "type": "text",
          "primaryKey": false,
          "notNull": true,
          "autoincrement": false
        },
        "notes": {
          "name": "notes",
          "type": "text",
          "primaryKey": false,
          "notNull": false,
          "autoincrement": false
        },
        "purchase_date": {
          "name": "purchase_date",
          "type": "text",
          "primaryKey": false,
          "notNull": true,
          "autoincrement": false
        },
        "total_amount_cents": {
          "name": "total_amount_cents",
          "type": "integer",
          "primaryKey": false,
          "notNull": true,
          "autoincrement": false
        },
        "installment_count": {
          "name": "installment_count",
          "type": "integer",
          "primaryKey": false,
          "notNull": true,
          "autoincrement": false
        },
        "first_invoice_month": {
          "name": "first_invoice_month",
          "type": "text",
          "primaryKey": false,
          "notNull": true,
          "autoincrement": false
        },
        "created_at": {
          "name": "created_at",
          "type": "integer",
          "primaryKey": false,
          "notNull": true,
          "autoincrement": false,
          "default": "(unixepoch() * 1000)"
        },
        "updated_at": {
          "name": "updated_at",
          "type": "integer",
          "primaryKey": false,
          "notNull": true,
          "autoincrement": false,
          "default": "(unixepoch() * 1000)"
        }
      },
      "indexes": {
        "credit_card_charges_account_idx": {
          "name": "credit_card_charges_account_idx",
          "columns": [
            "account_id"
          ],
          "isUnique": false
        },
        "credit_card_charges_category_idx": {
          "name": "credit_card_charges_category_idx",
          "columns": [
            "category_id"
          ],
          "isUnique": false
        },
        "credit_card_charges_purchase_date_idx": {
          "name": "credit_card_charges_purchase_date_idx",
          "columns": [
            "purchase_date"
          ],
          "isUnique": false
        },
        "credit_card_charges_first_invoice_idx": {
          "name": "credit_card_charges_first_invoice_idx",
          "columns": [
            "first_invoice_month"
          ],
          "isUnique": false
        }
      },
      "foreignKeys": {
        "credit_card_charges_account_id_accounts_id_fk": {
          "name": "credit_card_charges_account_id_accounts_id_fk",
          "tableFrom": "credit_card_charges",
          "tableTo": "accounts",
          "columnsFrom": [
            "account_id"
          ],
          "columnsTo": [
            "id"
          ],
          "onDelete": "restrict",
          "onUpdate": "no action"
        },
        "credit_card_charges_category_id_categories_id_fk": {
          "name": "credit_card_charges_category_id_categories_id_fk",
          "tableFrom": "credit_card_charges",
          "tableTo": "categories",
          "columnsFrom": [
            "category_id"
          ],
          "columnsTo": [
            "id"
          ],
          "onDelete": "restrict",
          "onUpdate": "no action"
        }
      },
      "compositePrimaryKeys": {},
      "uniqueConstraints": {},
      "checkConstraints": {}
    },
    "credit_card_installments": {
      "name": "credit_card_installments",
      "columns": {
        "id": {
          "name": "id",
          "type": "text",
          "primaryKey": true,
          "notNull": true,
          "autoincrement": false
        },
        "charge_id": {
          "name": "charge_id",
          "type": "text",
          "primaryKey": false,
          "notNull": true,
          "autoincrement": false
        },
        "installment_number": {
          "name": "installment_number",
          "type": "integer",
          "primaryKey": false,
          "notNull": true,
          "autoincrement": false
        },
        "amount_cents": {
          "name": "amount_cents",
          "type": "integer",
          "primaryKey": false,
          "notNull": true,
          "autoincrement": false
        },
        "invoice_month": {
          "name": "invoice_month",
          "type": "text",
          "primaryKey": false,
          "notNull": true,
          "autoincrement": false
        },
        "created_at": {
          "name": "created_at",
          "type": "integer",
          "primaryKey": false,
          "notNull": true,
          "autoincrement": false,
          "default": "(unixepoch() * 1000)"
        },
        "updated_at": {
          "name": "updated_at",
          "type": "integer",
          "primaryKey": false,
          "notNull": true,
          "autoincrement": false,
          "default": "(unixepoch() * 1000)"
        }
      },
      "indexes": {
        "credit_card_installments_charge_idx": {
          "name": "credit_card_installments_charge_idx",
          "columns": [
            "charge_id"
          ],
          "isUnique": false
        },
        "credit_card_installments_invoice_month_idx": {
          "name": "credit_card_installments_invoice_month_idx",
          "columns": [
            "invoice_month"
          ],
          "isUnique": false
        },
        "credit_card_installments_charge_number_unique": {
          "name": "credit_card_installments_charge_number_unique",
          "columns": [
            "charge_id",
            "installment_number"
          ],
          "isUnique": true
        }
      },
      "foreignKeys": {
        "credit_card_installments_charge_id_credit_card_charges_id_fk": {
          "name": "credit_card_installments_charge_id_credit_card_charges_id_fk",
          "tableFrom": "credit_card_installments",
          "tableTo": "credit_card_charges",
          "columnsFrom": [
            "charge_id"
          ],
          "columnsTo": [
            "id"
          ],
          "onDelete": "cascade",
          "onUpdate": "no action"
        }
      },
      "compositePrimaryKeys": {},
      "uniqueConstraints": {},
      "checkConstraints": {}
    },
    "investment_portfolio": {
      "name": "investment_portfolio",
      "columns": {
        "id": {
          "name": "id",
          "type": "text",
          "primaryKey": true,
          "notNull": true,
          "autoincrement": false
        },
        "current_balance_cents": {
          "name": "current_balance_cents",
          "type": "integer",
          "primaryKey": false,
          "notNull": true,
          "autoincrement": false
        },
        "monthly_contribution_cents": {
          "name": "monthly_contribution_cents",
          "type": "integer",
          "primaryKey": false,
          "notNull": true,
          "autoincrement": false
        },
        "expected_monthly_rate_bps": {
          "name": "expected_monthly_rate_bps",
          "type": "integer",
          "primaryKey": false,
          "notNull": true,
          "autoincrement": false
        },
        "reference_date": {
          "name": "reference_date",
          "type": "text",
          "primaryKey": false,
          "notNull": true,
          "autoincrement": false
        },
        "created_at": {
          "name": "created_at",
          "type": "integer",
          "primaryKey": false,
          "notNull": true,
          "autoincrement": false,
          "default": "(unixepoch() * 1000)"
        },
        "updated_at": {
          "name": "updated_at",
          "type": "integer",
          "primaryKey": false,
          "notNull": true,
          "autoincrement": false,
          "default": "(unixepoch() * 1000)"
        }
      },
      "indexes": {},
      "foreignKeys": {},
      "compositePrimaryKeys": {},
      "uniqueConstraints": {},
      "checkConstraints": {}
    },
    "recurring_templates": {
      "name": "recurring_templates",
      "columns": {
        "id": {
          "name": "id",
          "type": "text",
          "primaryKey": true,
          "notNull": true,
          "autoincrement": false
        },
        "account_id": {
          "name": "account_id",
          "type": "text",
          "primaryKey": false,
          "notNull": true,
          "autoincrement": false
        },
        "category_id": {
          "name": "category_id",
          "type": "text",
          "primaryKey": false,
          "notNull": true,
          "autoincrement": false
        },
        "type": {
          "name": "type",
          "type": "text",
          "primaryKey": false,
          "notNull": true,
          "autoincrement": false
        },
        "status": {
          "name": "status",
          "type": "text",
          "primaryKey": false,
          "notNull": true,
          "autoincrement": false,
          "default": "'active'"
        },
        "amount_cents": {
          "name": "amount_cents",
          "type": "integer",
          "primaryKey": false,
          "notNull": true,
          "autoincrement": false
        },
        "day_of_month": {
          "name": "day_of_month",
          "type": "integer",
          "primaryKey": false,
          "notNull": true,
          "autoincrement": false
        },
        "start_month": {
          "name": "start_month",
          "type": "text",
          "primaryKey": false,
          "notNull": true,
          "autoincrement": false
        },
        "end_month": {
          "name": "end_month",
          "type": "text",
          "primaryKey": false,
          "notNull": false,
          "autoincrement": false
        },
        "last_generated_month": {
          "name": "last_generated_month",
          "type": "text",
          "primaryKey": false,
          "notNull": false,
          "autoincrement": false
        },
        "description": {
          "name": "description",
          "type": "text",
          "primaryKey": false,
          "notNull": true,
          "autoincrement": false
        },
        "created_at": {
          "name": "created_at",
          "type": "integer",
          "primaryKey": false,
          "notNull": true,
          "autoincrement": false,
          "default": "(unixepoch() * 1000)"
        },
        "updated_at": {
          "name": "updated_at",
          "type": "integer",
          "primaryKey": false,
          "notNull": true,
          "autoincrement": false,
          "default": "(unixepoch() * 1000)"
        }
      },
      "indexes": {
        "recurring_templates_account_idx": {
          "name": "recurring_templates_account_idx",
          "columns": [
            "account_id"
          ],
          "isUnique": false
        },
        "recurring_templates_category_idx": {
          "name": "recurring_templates_category_idx",
          "columns": [
            "category_id"
          ],
          "isUnique": false
        }
      },
      "foreignKeys": {
        "recurring_templates_account_id_accounts_id_fk": {
          "name": "recurring_templates_account_id_accounts_id_fk",
          "tableFrom": "recurring_templates",
          "tableTo": "accounts",
          "columnsFrom": [
            "account_id"
          ],
          "columnsTo": [
            "id"
          ],
          "onDelete": "restrict",
          "onUpdate": "no action"
        },
        "recurring_templates_category_id_categories_id_fk": {
          "name": "recurring_templates_category_id_categories_id_fk",
          "tableFrom": "recurring_templates",
          "tableTo": "categories",
          "columnsFrom": [
            "category_id"
          ],
          "columnsTo": [
            "id"
          ],
          "onDelete": "restrict",
          "onUpdate": "no action"
        }
      },
      "compositePrimaryKeys": {},
      "uniqueConstraints": {},
      "checkConstraints": {}
    },
    "transactions": {
      "name": "transactions",
      "columns": {
        "id": {
          "name": "id",
          "type": "text",
          "primaryKey": true,
          "notNull": true,
          "autoincrement": false
        },
        "account_id": {
          "name": "account_id",
          "type": "text",
          "primaryKey": false,
          "notNull": true,
          "autoincrement": false
        },
        "category_id": {
          "name": "category_id",
          "type": "text",
          "primaryKey": false,
          "notNull": true,
          "autoincrement": false
        },
        "recurring_template_id": {
          "name": "recurring_template_id",
          "type": "text",
          "primaryKey": false,
          "notNull": false,
          "autoincrement": false
        },
        "type": {
          "name": "type",
          "type": "text",
          "primaryKey": false,
          "notNull": true,
          "autoincrement": false
        },
        "status": {
          "name": "status",
          "type": "text",
          "primaryKey": false,
          "notNull": true,
          "autoincrement": false,
          "default": "'posted'"
        },
        "amount_cents": {
          "name": "amount_cents",
          "type": "integer",
          "primaryKey": false,
          "notNull": true,
          "autoincrement": false
        },
        "transaction_date": {
          "name": "transaction_date",
          "type": "text",
          "primaryKey": false,
          "notNull": true,
          "autoincrement": false
        },
        "competence_month": {
          "name": "competence_month",
          "type": "text",
          "primaryKey": false,
          "notNull": true,
          "autoincrement": false
        },
        "description": {
          "name": "description",
          "type": "text",
          "primaryKey": false,
          "notNull": true,
          "autoincrement": false
        },
        "notes": {
          "name": "notes",
          "type": "text",
          "primaryKey": false,
          "notNull": false,
          "autoincrement": false
        },
        "created_at": {
          "name": "created_at",
          "type": "integer",
          "primaryKey": false,
          "notNull": true,
          "autoincrement": false,
          "default": "(unixepoch() * 1000)"
        },
        "updated_at": {
          "name": "updated_at",
          "type": "integer",
          "primaryKey": false,
          "notNull": true,
          "autoincrement": false,
          "default": "(unixepoch() * 1000)"
        }
      },
      "indexes": {
        "transactions_account_idx": {
          "name": "transactions_account_idx",
          "columns": [
            "account_id"
          ],
          "isUnique": false
        },
        "transactions_category_idx": {
          "name": "transactions_category_idx",
          "columns": [
            "category_id"
          ],
          "isUnique": false
        },
        "transactions_competence_idx": {
          "name": "transactions_competence_idx",
          "columns": [
            "competence_month"
          ],
          "isUnique": false
        },
        "transactions_recurring_month_unique": {
          "name": "transactions_recurring_month_unique",
          "columns": [
            "recurring_template_id",
            "competence_month"
          ],
          "isUnique": true
        }
      },
      "foreignKeys": {
        "transactions_account_id_accounts_id_fk": {
          "name": "transactions_account_id_accounts_id_fk",
          "tableFrom": "transactions",
          "tableTo": "accounts",
          "columnsFrom": [
            "account_id"
          ],
          "columnsTo": [
            "id"
          ],
          "onDelete": "restrict",
          "onUpdate": "no action"
        },
        "transactions_category_id_categories_id_fk": {
          "name": "transactions_category_id_categories_id_fk",
          "tableFrom": "transactions",
          "tableTo": "categories",
          "columnsFrom": [
            "category_id"
          ],
          "columnsTo": [
            "id"
          ],
          "onDelete": "restrict",
          "onUpdate": "no action"
        },
        "transactions_recurring_template_id_recurring_templates_id_fk": {
          "name": "transactions_recurring_template_id_recurring_templates_id_fk",
          "tableFrom": "transactions",
          "tableTo": "recurring_templates",
          "columnsFrom": [
            "recurring_template_id"
          ],
          "columnsTo": [
            "id"
          ],
          "onDelete": "set null",
          "onUpdate": "no action"
        }
      },
      "compositePrimaryKeys": {},
      "uniqueConstraints": {},
      "checkConstraints": {}
    },
    "transfers": {
      "name": "transfers",
      "columns": {
        "id": {
          "name": "id",
          "type": "text",
          "primaryKey": true,
          "notNull": true,
          "autoincrement": false
        },
        "from_account_id": {
          "name": "from_account_id",
          "type": "text",
          "primaryKey": false,
          "notNull": true,
          "autoincrement": false
        },
        "to_account_id": {
          "name": "to_account_id",
          "type": "text",
          "primaryKey": false,
          "notNull": true,
          "autoincrement": false
        },
        "amount_cents": {
          "name": "amount_cents",
          "type": "integer",
          "primaryKey": false,
          "notNull": true,
          "autoincrement": false
        },
        "transfer_date": {
          "name": "transfer_date",
          "type": "text",
          "primaryKey": false,
          "notNull": true,
          "autoincrement": false
        },
        "competence_month": {
          "name": "competence_month",
          "type": "text",
          "primaryKey": false,
          "notNull": true,
          "autoincrement": false
        },
        "description": {
          "name": "description",
          "type": "text",
          "primaryKey": false,
          "notNull": true,
          "autoincrement": false
        },
        "created_at": {
          "name": "created_at",
          "type": "integer",
          "primaryKey": false,
          "notNull": true,
          "autoincrement": false,
          "default": "(unixepoch() * 1000)"
        },
        "updated_at": {
          "name": "updated_at",
          "type": "integer",
          "primaryKey": false,
          "notNull": true,
          "autoincrement": false,
          "default": "(unixepoch() * 1000)"
        }
      },
      "indexes": {
        "transfers_from_account_idx": {
          "name": "transfers_from_account_idx",
          "columns": [
            "from_account_id"
          ],
          "isUnique": false
        },
        "transfers_to_account_idx": {
          "name": "transfers_to_account_idx",
          "columns": [
            "to_account_id"
          ],
          "isUnique": false
        },
        "transfers_competence_idx": {
          "name": "transfers_competence_idx",
          "columns": [
            "competence_month"
          ],
          "isUnique": false
        }
      },
      "foreignKeys": {
        "transfers_from_account_id_accounts_id_fk": {
          "name": "transfers_from_account_id_accounts_id_fk",
          "tableFrom": "transfers",
          "tableTo": "accounts",
          "columnsFrom": [
            "from_account_id"
          ],
          "columnsTo": [
            "id"
          ],
          "onDelete": "restrict",
          "onUpdate": "no action"
        },
        "transfers_to_account_id_accounts_id_fk": {
          "name": "transfers_to_account_id_accounts_id_fk",
          "tableFrom": "transfers",
          "tableTo": "accounts",
          "columnsFrom": [
            "to_account_id"
          ],
          "columnsTo": [
            "id"
          ],
          "onDelete": "restrict",
          "onUpdate": "no action"
        }
      },
      "compositePrimaryKeys": {},
      "uniqueConstraints": {},
      "checkConstraints": {}
    }
  },
  "views": {},
  "enums": {},
  "_meta": {
    "schemas": {},
    "tables": {},
    "columns": {}
  },
  "internal": {
    "indexes": {}
  }
}